cellflow/__init__.py
cellflow/_constants.py
cellflow/_logging.py
cellflow/_types.py
cellflow/datasets.py
cellflow/utils.py
cellflow/data/__init__.py
cellflow/data/_data.py
cellflow/data/_dataloader.py
cellflow/data/_datamanager.py
cellflow/data/_utils.py
cellflow/external/__init__.py
cellflow/external/_scvi.py
cellflow/external/_scvi_utils.py
cellflow/metrics/__init__.py
cellflow/metrics/_metrics.py
cellflow/model/__init__.py
cellflow/model/_cellflow.py
cellflow/model/_utils.py
cellflow/networks/__init__.py
cellflow/networks/_set_encoders.py
cellflow/networks/_utils.py
cellflow/networks/_velocity_field.py
cellflow/plotting/__init__.py
cellflow/plotting/_plotting.py
cellflow/plotting/_utils.py
cellflow/preprocessing/__init__.py
cellflow/preprocessing/_gene_emb.py
cellflow/preprocessing/_pca.py
cellflow/preprocessing/_preprocessing.py
cellflow/preprocessing/_wknn.py
cellflow/solvers/__init__.py
cellflow/solvers/_genot.py
cellflow/solvers/_otfm.py
cellflow/training/__init__.py
cellflow/training/_callbacks.py
cellflow/training/_trainer.py
cellflow/training/_utils.py
cellflow_tools-0.0.6.dist-info/METADATA
cellflow_tools-0.0.6.dist-info/WHEEL
cellflow_tools-0.0.6.dist-info/licenses/LICENSE
cellflow_tools-0.0.6.dist-info/RECORD
